save_thread_result/__init__.py
save_thread_result-0.1.1.post1.dist-info/METADATA
save_thread_result-0.1.1.post1.dist-info/WHEEL
save_thread_result-0.1.1.post1.dist-info/top_level.txt
save_thread_result-0.1.1.post1.dist-info/RECORD
